voltus/__init__.py
voltus/client.py
voltus/energy_data.csv
voltus-0.0.8.dist-info/LICENSE
voltus-0.0.8.dist-info/METADATA
voltus-0.0.8.dist-info/WHEEL
voltus-0.0.8.dist-info/RECORD
