Metadata-Version: 2.1
Name: voltus
Version: 0.0.8
Summary: A Python client for the Voltus API
License: MIT
Author: Carlos Tarjano
Author-email: carlos.t.santos@inesctec.pt
Requires-Python: >=3.10,<4.0
Classifier: License :: OSI Approved :: MIT License
Classifier: Programming Language :: Python :: 3
Classifier: Programming Language :: Python :: 3.10
Classifier: Programming Language :: Python :: 3.11
Classifier: Programming Language :: Python :: 3.12
Classifier: Programming Language :: Python :: 3.13
Requires-Dist: pandas (>=2.2.3,<3.0.0)
Requires-Dist: pyarrow (>=19.0.1,<20.0.0)
Requires-Dist: pydantic (>=2.11.4,<3.0.0)
Requires-Dist: pytest (>=8.3.5,<9.0.0)
Requires-Dist: python-dotenv (>=1.0.1,<2.0.0)
Requires-Dist: requests (>=2.32.3,<3.0.0)
